sphinx_panels/__init__.py
sphinx_panels/button.py
sphinx_panels/dropdown.py
sphinx_panels/icons.py
sphinx_panels/panels.py
sphinx_panels/tabs.py
sphinx_panels/utils.py
sphinx_panels/_css/__init__.py
sphinx_panels/_css/panels-bootstrap.5fd3999ee7762ccc51105388f4a9d115.css
sphinx_panels/_css/panels-main.c949a650a448cc0ae9fd3441c0e17fb0.css
sphinx_panels/data/LICENSE
sphinx_panels/data/opticons.json
sphinx_panels/scss/bootstrap/_badge.scss
sphinx_panels/scss/bootstrap/_borders.scss
sphinx_panels/scss/bootstrap/_buttons.scss
sphinx_panels/scss/bootstrap/_cards.scss
sphinx_panels/scss/bootstrap/_colors.scss
sphinx_panels/scss/bootstrap/_grids.scss
sphinx_panels/scss/bootstrap/_overrides.scss
sphinx_panels/scss/bootstrap/index.scss
sphinx_panels/scss/panels/_dropdown.scss
sphinx_panels/scss/panels/_icons.scss
sphinx_panels/scss/panels/_tabs.scss
sphinx_panels/scss/panels/index.scss
sphinx_panels-0.6.0.dist-info/LICENSE
sphinx_panels-0.6.0.dist-info/METADATA
sphinx_panels-0.6.0.dist-info/WHEEL
sphinx_panels-0.6.0.dist-info/top_level.txt
sphinx_panels-0.6.0.dist-info/RECORD
