Metadata-Version: 2.1
Name: sphinx-panels
Version: 0.6.0
Summary: A sphinx extension for creating panels in a grid layout.
Home-page: https://github.com/executablebooks/sphinx-panels
Author: Chris Sewell
Author-email: chrisj_sewell@hotmail.com
License: MIT
Project-URL: Documentation, https://sphinx-panels.readthedocs.io
Keywords: sphinx html bootstrap grid card dropdown button badge
Platform: UNKNOWN
Classifier: License :: OSI Approved :: MIT License
Classifier: Programming Language :: Python :: 3
Classifier: Topic :: Software Development :: Libraries :: Python Modules
Classifier: Framework :: Sphinx :: Extension
Provides-Extra: themes
Provides-Extra: code_style
Provides-Extra: testing
Provides-Extra: live-dev
